LICENSE
README.md
setup.cfg
setup.py
src/album/__init__.py
src/album/server/__init__.py
src/album/server/argument_parsing.py
src/album/server/server.py
src/album_server.egg-info/PKG-INFO
src/album_server.egg-info/SOURCES.txt
src/album_server.egg-info/dependency_links.txt
src/album_server.egg-info/entry_points.txt
src/album_server.egg-info/requires.txt
src/album_server.egg-info/top_level.txt
test/test_common.py