Metadata-Version: 2.1
Name: album-server
Version: 0.1.0
Summary: album plugin for controlling album via a server and REST API
Home-page: https://gitlab.com/album-app/album-server
Author: Kyle Harrington, Jan Philipp Albrecht, Deborah Schmidt
Maintainer: Kyle Harrington, Jan Philipp Albrecht, Deborah Schmidt
Maintainer-email: album@kyleharrington.com
License: MIT
Project-URL: Source, https://gitlab.com/album-app/album-server
Project-URL: Tracker, https://gitlab.com/album-app/album-server/issues
Keywords: virtual,environments,imaging,data analysis
Platform: any
Classifier: Development Status :: 3 - Alpha
Classifier: License :: OSI Approved :: MIT License
Classifier: Operating System :: MacOS :: MacOS X
Classifier: Operating System :: Microsoft :: Windows
Classifier: Operating System :: POSIX
Classifier: Programming Language :: Python :: 3.8
Classifier: Programming Language :: Python :: 3.9
Classifier: Programming Language :: Python :: Implementation :: PyPy
Classifier: Topic :: Utilities
Requires-Python: >=3.7
License-File: LICENSE
